yarr/__init__.py
yarr/admin.py
yarr/apps.py
yarr/constants.py
yarr/decorators.py
yarr/forms.py
yarr/managers.py
yarr/models.py
yarr/settings.py
yarr/urls.py
yarr/utils.py
yarr/views.py
yarr/management/__init__.py
yarr/management/commands/__init__.py
yarr/management/commands/check_feeds.py
yarr/management/commands/import_opml.py
yarr/management/commands/yarr_clean.py
yarr/migrations/0001_initial.py
yarr/migrations/__init__.py
yarr/static/yarr/index.css
yarr/static/yarr/index.js
yarr/static/yarr/index.js.map
yarr/templates/yarr/base.html
yarr/templates/yarr/base_all.html
yarr/templates/yarr/base_manage.html
yarr/templates/yarr/confirm.html
yarr/templates/yarr/feed_add.html
yarr/templates/yarr/feed_edit.html
yarr/templates/yarr/feeds.html
yarr/templates/yarr/list_entries.html
yarr/templates/yarr/include/entry.html
yarr/templates/yarr/include/form_feed_add.html
yarr/templates/yarr/include/form_feed_edit.html
django_yarr-0.7.0.dist-info/LICENSE
django_yarr-0.7.0.dist-info/METADATA
django_yarr-0.7.0.dist-info/WHEEL
django_yarr-0.7.0.dist-info/top_level.txt
django_yarr-0.7.0.dist-info/RECORD
