Metadata-Version: 2.1
Name: django-yarr
Version: 0.7.0
Summary: A lightweight customisable RSS reader for Django
Home-page: https://radiac.net/projects/django-yarr/
Author: Richard Terry
Author-email: code@radiac.net
License: BSD
Project-URL: Documentation, https://radiac.net/projects/django-yarr/
Project-URL: Source, https://github.com/radiac/django-yarr
Project-URL: Tracker, https://github.com/radiac/django-yarr/issues
Keywords: django rss
Platform: UNKNOWN
Classifier: Development Status :: 4 - Beta
Classifier: Environment :: Web Environment
Classifier: Framework :: Django
Classifier: Framework :: Django :: 2.2
Classifier: Framework :: Django :: 3.0
Classifier: Framework :: Django :: 3.1
Classifier: Intended Audience :: Developers
Classifier: License :: OSI Approved :: BSD License
Classifier: Operating System :: OS Independent
Classifier: Programming Language :: Python
Classifier: Programming Language :: Python :: 3
Classifier: Programming Language :: Python :: 3 :: Only
Classifier: Programming Language :: Python :: 3.7
Classifier: Programming Language :: Python :: 3.8
Requires-Python: >=3.7
License-File: LICENSE
Requires-Dist: Django (>=2.2)
Requires-Dist: django-yaa-settings
Requires-Dist: bleach[css] (>=5.0.0)
Requires-Dist: feedparser (>=6.0.0)
